{
  "2025_22_00001": {
    "url": "https://www.psp.cz/eknih/2025ps/stenprot/022schuz/s022001.htm#r1",
    "cele_jmeno": "Tomio Okamura",
    "poradi": 1,
    "text": "Vážené paní poslankyně, vážení páni poslanci, vážení členové vlády, zahajuji 22. schůzi Poslanecké sněmovny a všechny vás vítám.\nAby byla zaznamenána naše účast, nejprve vás odhlásím a přihlašte se svými identifikačními kartami, a případně mi oznámili, kdo žádá o vydání náhradní karty. \nTuto schůzi jsem svolal podle § 51 odst. 4 našeho jednacího řádu na základě žádosti 90 poslanců. Pozvánka vám byla rozeslána v pátek 5. června tohoto roku elektronickou poštou.\nNyní přistoupíme k určení dvou ověřovatelů této schůze. \n \nNavrhuji, abychom určili poslankyni Michaelu Moricovou a poslankyni Barboru Rázgu. Má někdo jiný návrh? Žádný jiný návrh nevidím. Ještě jsem zagongoval, tak dáme prostor, aby ještě dorazili další poslanci.\nZahajuji hlasování. Kdo je pro? Kdo je proti?\nHlasování číslo 1, přihlášeno 140 poslanců, pro 134, proti 4. Návrh byl přijat.\n \nKonstatuji tedy, že jsme ověřovatelkami 22. schůze Poslanecké sněmovny určili poslankyni Michaelu Moricovou a poslankyni Barboru Rázga. \nSděluji, že do zahájení schůze požádali omluvení své neúčasti na jednání tito poslanci: Baxa Martin do 12.30 z pracovních důvodů, Brzesková Monika od 16 hodin z osobních důvodů, Černochová Jana celý jednací den – zahraniční cesta, Demjanová Jana celý jednací den – zahraniční cesta, Doležal Tomáš celý jednací den – zahraniční cesta, Dvořák Karel od 15 hodin – pracovní důvody, Fiala Petr celý jednací den – osobní důvody, Flek Josef od 13 hodin – pracovní důvody, Fridrich Stanislav celý jednací den – zdravotní důvody, Hrnčíř Jan celý jednací den – zahraniční cesta, Jakob Jan od 16 hodin – osobní důvody, Janda Jakub celý jednací den – zahraniční cesta, Kolek Vladimír celý jednací den – zdravotní důvody, Mádlová Ivana celý jednací den – rodinné důvody, Majerová Zuzana celý jednací den – rodinné důvody, Nerušil Josef od 16 do 21 hodin – pracovní důvody, Okamura Hayato celý jednací den – pracovní důvody, Olšáková Eliška celý jednací den – osobní důvody, Oulehlová Renata od 15 hodin – zdravotní důvody, Outrata Pavel celý jednací den – rodinné důvody, Samaš Miroslav do 13 hodin – pracovní důvody, Sedláčková Gabriela celý jednací den – zahraniční cesta, Svárovská Gabriela od 12 do 15 hodin – pracovní důvody, Šmída Martin od 15 hodin – osobní důvody, Tureček Karel celý jednací den – rodinné důvody, Vojáček Jiří do 15 hodin – pracovní důvody, Volpe Samuel celý jednací den – zahraniční cesta, Weimerová Ester celý jednací den – zahraniční cesta, Wenzl Lubomír celý jednací den – rodinné důvody.\nBabiš Andrej celý jednací den – pracovní důvody, Bednárik Ivan do 15 hodin – pracovní důvody, Červený Igor celý jednací den – pracovní důvody, Havlíček Karel celý jednací den – pracovní důvody, Plaga Robert do 13.30 – pracovní důvody, Schillerová Alena celý jednací den – pracovní důvody, Tejc Jeroným celý jednací den – pracovní důvody, Vojtěch Adam celý jednací den – pracovní důvody, Zůna Jaromír celý jednací den – pracovní důvody.\nVážené paní poslankyně, vážení páni poslanci, vážení členové vlády, před stanovením pořadu 22. schůze Poslanecké sněmovny ještě připomínám, že v 15 hodin bude zahájena 23. schůze Poslanecké sněmovny. \nNyní přistoupíme ke stanovení pořadu 22. schůze, jehož návrh je uveden na pozvánce. Připomínám, že podle § 54 odst. 7 zákona o jednacím řádu rozhodne Sněmovna pouze o pořadu uvedeném v žádosti. Nelze navrhnout žádnou změnu ani doplnění pořadu, rovněž tak nelze rozšiřovat schválený pořad. \nNyní by vystoupili poslanci s přednostním právem a jako prvního požádám o vystoupení ministra zemědělství Martina Šebestyána.\nProsím o klid v jednacím sále, protože už začnou vystupovat poslanci. Já to vždycky zvládnu v úvodu, ale poslance necháme vystoupit v klidu.\nPan ministr Martin Šebestyán a připraví se paní ministryně Zuzana Mrázová a následně pan předseda Vít Rakušan.\nProsím, máte slovo.\nProsím o klid ještě jednou, o klid v jednacím sále, prosím o úplný klid v jednacím sále. Ještě jednou prosím o klid.\nPane ministře, prosím.\nJeště jednou (Zvoní zvonkem.).\nTak prosím."
  },
  "2025_22_00002": {
    "url": "https://www.psp.cz/eknih/2025ps/stenprot/022schuz/s022001.htm#r2",
    "cele_jmeno": "Martin Šebestyán",
    "poradi": 2,
    "text": "Vážený pane předsedo, vážené paní poslankyně, vážení páni poslanci, dovolte, abych ve svém vystoupení shrnul problematiku k takzvanému střetu zájmů z pohledu Ministerstva zemědělství, tedy za oblast zemědělských podpor. \nPřed dvěma týdny se v médiích objevil dopis DG REGIO, podle jejichž výkladu se doporučuje postup k vykazování výdajů společnostem z koncernu Agrofert a který zmiňuje i zemědělské dotační fondy. Podle těchto názorů by české orgány neměly Evropské komisi vykazovat od 9. prosince 2025 žádné výdaje související s dotacemi společnostem z koncernu Agrofert. \nTento dopis je vykládán tak, že rozhodnutím Evropské komise došlo k pozastavení plateb, takový výklad je však nesprávný. Zmíněný dopis DG REGIO je pracovní komunikací mezi tímto ředitelstvím Evropské komise a dotčenými subjekty v členském státě – a zde zdůrazňuji, že je právně nezávazný. (Předsedající: Prosím o klid v jednacím sále.) Pozastavit platby je oprávněna pouze Evropská komise, a to oficiálním právním aktem, takzvaným prováděcím rozhodnutím, které je následně ze strany členského státu možné podrobit soudnímu přezkumu před Soudním dvorem.\nTaké v průběhu auditního šetření týkajícího se střetu zájmů v letech 2019 až 2022 probíhala mezi DG AGRI a DG REGIO a dotčenými orgány členského státu neformální komunikace. Zde je třeba zdůraznit, že předmětem tohoto historického auditního šetření nikdy nebyly nárokové dotace, tedy přímé platby. Tyto platby byly a jsou po celou dobu ze strany Evropské komise propláceny. \nChci uvést, že nad rámec komunikace s DG REGIO, které byla věnována takřka veškerá pozornost, probíhala od 11. března 2026 – a nadále probíhá – ze strany Státního zemědělského intervenčního fondu komunikace s DG AGRI týkající se problematiky střetu zájmů. Rád bych zrekapituloval veškeré kroky a milníky, které byly v souvislosti s problematikou střetu zájmů v rezortu zemědělství učiněny, jelikož jejich pochopení je klíčové pro porozumění této problematiky jakožto celku. ***"
  },
  "2025_22_00003": {
    "url": "https://www.psp.cz/eknih/2025ps/stenprot/022schuz/s022002.htm#r1",
    "cele_jmeno": "Tomio Okamura",
    "poradi": 3,
    "text": "Nyní vystoupí... Děkuji panu ministrovi Šebestyánovi a nyní vystoupí paní ministryně pro místní rozvoj Zuzana Mrázová. Prosím, paní ministryně, máte slovo."
  },
  "2025_22_00004": {
    "url": "https://www.psp.cz/eknih/2025ps/stenprot/022schuz/s022002.htm#r2",
    "cele_jmeno": "Zuzana Mrázová",
    "poradi": 4,
    "text": "Děkuji. Vážený pane předsedající, vážené poslankyně, vážení poslanci. Dovolte mi nejprve stručně představit roli Ministerstva pro místní rozvoj v aktuálně řešené problematice možného střetu zájmů v rámci evropských fondů a popsat dosavadní komunikaci s Evropskou komisí. Za zásadní považuji rozlišit odlišný přístup a pohled na evropské fondy politiky soudržnosti neboli kohezní politiky a oblast společné zemědělské politiky. \nMinisterstvo pro místní rozvoj plní v oblasti fondů Evropské unie roli Národního orgánu pro koordinaci. V této pozici zastřešuje koordinační a metodickou činnost vůči řídícím orgánům operačních programů a zajišťuje jednotnou komunikaci s Evropskou komisí za oblast politiky soudržnosti. \nRáda bych ale zdůraznila, že Ministerstvo pro místní rozvoj má dvě odlišné role. Jednak je to koordinační a metodická role a pak také role poskytovatele dotací. Národní orgán pro koordinaci Ministerstva pro místní rozvoj, který mimo jiné koordinuje odpovědi na dotazy Evropské komise, nastavuje pravidla pro čerpání evropských prostředků, nicméně nemá rozhodovací pravomoci v jednotlivých dotačních řízeních. Odpovědnost za posouzení případného střetu zájmů u konkrétních žádostí leží vždy na příslušném poskytovateli dotace, tedy na řídícím orgánu daného operačního programu. \nZde vystupuje MMR do druhé role, a to řídícího orgánu programu v gesci ministerstva, kterým je Integrovaný regionální operační program, Program přeshraniční spolupráce Česko–Polsko a operační program Technická pomoc. Za všechny tyto tři programy mohu potvrdit, že společnost Agrofert, SynBiol ani Hartenberg aktuálně nefigurují mezi žadateli o dotace z programu řízených naším ministerstvem.\nV rámci koordinační role Ministerstva pro místní rozvoj je naší společnou odpovědností s Ministerstvem financí jako auditním orgánem a ve spolupráci s ostatními rezorty a zapojenými subjekty nastavit pravidla pro čerpání evropských fondů tak, aby odpovídala požadavkům národní i evropské legislativy. Ministerstvo pro místní rozvoj pak v rámci své působnosti dále koordinuje komunikaci s Evropskou komisí, jak jsem již říkala, ale – a to opět – pouze pro politiku soudržnosti. Důrazně je tak třeba uvést, že za oblast společné zemědělské politiky, tedy za zemědělské dotace, odpovídá i vzhledem k odlišné právní úpravě zemědělských fondů na úrovni Evropské unie Ministerstvo zemědělství, a tudíž i problematika střetu zájmů je v této oblasti řešena samostatně Ministerstvem zemědělství. ***"
  },
  "2025_22_00005": {
    "url": "https://www.psp.cz/eknih/2025ps/stenprot/022schuz/s022003.htm#r1",
    "cele_jmeno": "Tomio Okamura",
    "poradi": 5,
    "text": "Nyní tedy vystoupí – děkuju paní ministryni – a vystoupí předseda STANu Vít Rakušan a připraví se, já přeču to pořadí, jo? Následně Matěj Ondřej Havel, Zdeněk Hřib, Martin Kupka, Marian Jurečka a potom Petr Macinka. Prosím, pane předsedo, máte slovo."
  },
  "2025_22_00006": {
    "url": "https://www.psp.cz/eknih/2025ps/stenprot/022schuz/s022003.htm#r2",
    "cele_jmeno": "Vít Rakušan",
    "poradi": 6,
    "text": "Děkuju za slovo, vážený pane předsedo. Dámy a pánové, kolegyně a kolegové, název téhle schůze, kterou navrhujeme, zní Ochrana českých občanů před placením rizikových dotací Agrofertu. \nA ještě předtím, než se dostanu k těm konkrétním věcem, jednu obecnou poznámku. My tady stále se pohybujeme v nějaké právnicko-akademické diskusi, co je a co není střet zájmů, stále se tady pohybujeme v různých právních výkladech. Já se za chvilku dostanu (k tomu), jak na tu právní nejistotu reaguje poslanecký návrh vládních poslanců, to je opravdu něco unikátního, ale k tomu za chvíli. \nAle přitom střet zájmů v té nejjednodušší linii a v tom nejjednodušším dualismu se dá vyřešit dvojím způsobem: buď být politikem, anebo být byznysmenem. Hledání nějakých řešení, která vždycky stojí někde na pomezí, vždycky budou vyvolávat nějakou míru nejistoty.\nMy jsme se tady bavili o riziku toho, že by čeští občané mohli doplatit na proplácení dotací Agrofertu, ale my už jsme v téhle chvíli bohužel dál. My nejsme u nějakého teoretického rizika, my jsme v téhle chvíli u reálné hrozby, a to není hrozba pro stát jako takový, to je hrozba pro jeho lidi, to je hrozba pro obyvatele, to je hrozba pro peněženky daňových poplatníků, každého z nás v téhle zemi. \nPamatujete si – a bylo to v devadesátkách populární, já se tady dívám, tady jsou mladí poslanci, ti už si (to) třeba tolik nepamatují – byli populární v ulicích skořápkáři. To byli takoví ti chlapíci, co měli takovou tu kuličku, která tam většinou ani nebyla, takhle hýbali těmi skořápkami (Názorně předvádí pohyb rukama.) a princip té hry byl založen na tom, že vy jako klient, který se nechal obrat o veškeré peníze, se díval jenom na jednu ruku toho skořápkáře, tu jste pozorovali. Druhá ruka mezitím dělala něco úplně jiného a tohle je přesně politika Andreje Babiše. Andrej Babiš jednou rukou dává, valorizuje, rozdává, zadlužuje a tou druhou rukou, kterou nesledujete při téhle podvodné hře – to vždycky byl podvod – tou si bere, a bere si opravdu hodně a bere si pro svůj byznys – nejenom pro Agrofert, ale hlavně pro něj. Tohle je to, čeho jsme v téhle chvíli svědky. \nPojďme si ale říct, a to na základě faktů a konkrétních čísel, na základě čeho tohle riziko a hrozba může být velmi přesně a jasně vykreslena. V letech 2017 až 2021 vyplatil stát firmám z holdingu Agrofert dotace v celkové výši přesahující 7 miliard korun, a to navzdory tomu, že Evropská komise v auditu z roku 2021 jednoznačně konstatovala, že premiér Babiš byl ve střetu zájmů a jako člen vlády rozhodoval o věcech, z nichž měl přímý osobní prospěch, navzdory tomu, že Nejvyšší správní soud opakovaně potvrdil, že svěřenecký fond RSVP Trust střet zájmů neodstranil – navzdory českému evropskému právu, to je potřeba podotknout. 7 miliard korun neoprávněně vyplacených dotací – to je zdokumentovaný fakt, to není žádné politické, nenávistné, opoziční, antibabišovské tvrzení.\nU některých dotací už soud rozhodl, že je na vymáhání pozdě. Máme tady drůbežárnu Schrom Farms holdingu Agrofert, vrátila dotaci 1,6 milionu korun, ale pražský Městský soud rozhodl, že vrátila neoprávněně, protože Státní zemědělský intervenční fond o vrácení požádal až po uplynutí té čtyřleté lhůty. Ministerstvo verdikt napadlo, a to u Nejvyššího správního soudu, kde odkazuje na desetiletou lhůtu podle zákona o Státním zemědělském intervenčním fondu. Ministr Šebestyán říká, že tentokrát promlčení nehrozí, ale lhůta vyprší v prosinci příštího roku, a řekněme si, že to není tak daleko, to je za chvíli – čas letí. \nA máme tady další závažný detail. Právní analýza Státního zemědělského intervenčního fondu jasně stanovila, že veškeré veřejné podpory z let 2017 až let 2021 pro společnosti, kde byl koncovým vlastníkem člen vlády, byly v rozporu se zákonem. Jak reagoval pan ministr Šebestyán na tuto analýzu, na toto zjištění? Cituji doslova, protože to stojí za to: „Právní analýza prostě nebyla dohledána“ – prostě se nenašla a ty částky, ty taky nesouhlasí. \n7 miliard korun, to je číslo, které si zaslouží, abychom se u něj zastavili. Je to 24 kilometrů nové dálnice, je to 14 nových základních škol, je to modernizace 27 oddělení regionálních nemocnic a je to 640 korun na každého občana v České republice, na každého z nás, z vás, na naše rodiče, na naše děti. To jsou ty peníze, které chybí. \nA tady mi dovolte malou zastávku. Vždyť my vidíme, co tahle vláda předvádí s rozpočtem – nejsou peníze vůbec na nic, ani na naši bezpečnost, na naši obranyschopnost, neplníme svoje závazky. Paní ministryně nám tady představí, že tenhle stát se bude bezlimitně zadlužovat pro příští generace. Teďka všechno bude jedno. Některé ty položky se schovají, protože v tom deficitu nebudou vidět, ale nic to nemění na tom, že to budou platit naše děti, že to budou platit naše vnoučata a možná i pravnoučata. ***"
  },
  "2025_22_00007": {
    "url": "https://www.psp.cz/eknih/2025ps/stenprot/022schuz/s022005.htm#r1",
    "cele_jmeno": "Tomio Okamura",
    "poradi": 7,
    "text": "Nyní vystoupí předseda TOP 09 Matěj Ondřej Havel a připraví se předseda Pirátů Zdeněk Hřib. Prosím, máte slovo."
  },
  "2025_22_00008": {
    "url": "https://www.psp.cz/eknih/2025ps/stenprot/022schuz/s022005.htm#r2",
    "cele_jmeno": "Matěj Ondřej Havel",
    "poradi": 8,
    "text": "Děkuju za slovo, pane předsedo. Vážené dámy, vážení pánové, vážení... (Otáčí se do ministerských lavic.), vážený pane ministře, škoda že tady není pan premiér. To jistě není náhoda, že se dneska omluvil, když máme schůzi zrovna, která řeší jeho střet zájmů. \nJá se na to podívám naprosto věcně, možná bez nějakých rozjitřených emocí, a rád bych tady některé věci pojmenoval – navzdory různým mediálním vlnám a mlhám, které vaříte – kolem landsmanšaftu, kolem sporů s prezidentem republiky o cestě necestě na shromáždění NATO, my nenecháme usnout tyto zásadní věci, které se možná snažíte tak trošku přikrýt a tak trošku nechat mediálně spát – a je to střet zájmů premiéra této země, který ještě zlehčujete a přiživujete tím pozměňovacím návrhem nebo tím návrhem zákona – já se k tomu ještě stručně vyjádřím.\nTak tedy věcně nejprve tři takové poznámky. Zákon o střetu zájmů, který v České republice platí, říká, že veřejný funkcionář se má zdržet jednání, při němž mohou jeho osobní zájmy ovlivnit výkon jeho funkce, a nesmí upřednostňovat svůj osobní zájem před zájmem veřejným. To za prvé.\nZa druhé dnes platí, že firmy, v nichž člen vlády nebo jím ovládaná osoba vlastní alespoň 25procentní podíl, se nesmějí účastnit zadávacích řízení a nesmějí dostat dotaci nebo investiční pobídku. Ministerstvo spravedlnosti tuto úpravu shrnuje jako zákaz účasti takových obchodních společností v zadávacích řízeních a zákaz poskytování dotací či investičních pobídek. \nA za třetí, Ústavní soud, ten už k takzvanému lex Babiš řekl jednu podstatnou věc. Tato úprava nikomu nebrání ucházet se o veřejnou funkci – samozřejmě, máme demokratický stát – ale říká, že když člověk veřejnou funkci zastává, a pokud ji získá, musí řešit střet mezi svou funkcí a svým majetkem. Stát se nemá přizpůsobovat soukromým zájmům uchazečů o moc. To tady ještě jednou ode mě uslyšíte v jiném kontextu. \nTakže my tady dnes řešíme na této mimořádné schůzi, zda v České republice platí, že veřejná moc slouží občanům, a to bez rozdílu, anebo zda se zákony budou ohýbat podle soukromého majetkového zájmu, v tomto případě přímo předsedy vlády. A to prosím samozřejmě není nic, co bychom mohli jako opoziční poslanci – nebo co byste vy i jako koaliční poslanci – mohli, měli v Poslanecké sněmovně tedy pominout. Pokud je premiér nebo pokud ten, kdo řídí vládu – což je logicky premiér, ovlivňuje ministry, nastavuje rozpočet, rozhoduje o směřování státní politiky, to je přirozené, pokud je tento člověk zároveň spojen s obřím holdingem, který čerpá veřejné peníze, pak tedy nestačí jenom říct: Věřte mi, já jsem to vyřešil. V právním státě, v sekulárním státě nestačí jenom taková víra. V právním státě musí být jasná pravidla, nezávislá kontrola, a hlavně ochrana peněz nás všech, daňových poplatníků. Pravidla platí pro všechny stejně, má to tak být.\nStřet zájmů premiéra Andreje Babiše je střetem veřejné a ekonomické moci. Agrofert si snad nikdo nemyslí, že je nějaká malá rodinná firma na okraji ekonomiky – je to obrovský holding zaměřený na zemědělství, chemii, potravinářství, a všichni to dobře známe, taková firma je přirozeně v přímém kontaktu se státem: skrze dotace, veřejné zakázky, regulace, zemědělskou politiku – a mohl bych pokračovat, a premiér není obyčejný ministr s nějakým jedním rezortem. Je to předseda vlády, který má logicky z ústavy v našem státě největší moc, a argument tedy, že předseda vlády přímo neřídí Ministerstvo zemědělství nebo zdravotnictví, je z politického hlediska absurdní. Premiér určuje složení vlády, určuje program, vládní priority, rozpočtové rámce a tak dále – premiér má přece vliv na celou vládu, nikoliv jenom na Úřad vlády. \nProblém není jenom ten faktický vliv, problém, který tady se snažíme v tom nasvěcovat, je i otřesení – a možná ztráta důvěry veřejnosti – ve stát, ve státní instituce, v pozici vlády, v pozici premiéra, ať v ní je kdokoliv v danou chvíli. I kdyby někdo tvrdil, že k žádnému konkrétnímu zásahu nedošlo, zůstává tady objektivní problém: Občan prostě neví, zda stát rozhoduje nestranně, a v právním státě nestačí, aby rozhodování bylo čisté, musí být taky důvěryhodné – to je to důležité, ta atmosféra.\nSvěřenský fond není automaticky vyřešením problému, to je podstatné. Vložení Agrofertu do RSVP Trustu je prezentováno jako definitivní řešení, ale Evropská komise žádá další vysvětlení, žádá další podklady a české úřady neprovedly dopředu důkladné posouzení, zda fond tedy skutečně odstraňuje střet zájmů premiéra – a to je jádro problému. Premiér tvrdí: Vyřešeno, ale kontrolní instituce říkají: Doložte to, že jste to vyřešil, a riziko pochopitelně potom dopadá na české daňové poplatníky. \nJestliže české orgány vyplatí Agrofertu peníze a Evropská komise je následně neproplatí, nebude to platit Andrej Babiš, nebude platit samozřejmě ani Agrofert, zaplatí to český státní rozpočet, zaplatí to každý jeden český daňový poplatník, občané a jeho, případně tedy státní instituce. \nLex Babiš z pera koaličních poslanců – to je další věc, kterou bych tady chtěl zmínit, protože jsem si našel v systému sněmovní tisk 221, který byl nahrán některými koaličními poslanci, třeba Filipem Turkem, který se dušuje, že pohlídá Andreje Babiše, tak tady už tedy popřel úplně všecko z toho, co před volbami vykřikoval. Myslím, že to tady má jednoznačně zaznít, protože to je oslabení zákona o střetu zájmů. \nCo tedy ten návrh dělá, naprosto technicky? V § 4b zákona o střetu zájmů ruší současný tvrdý zákaz účasti firem spojených s členem vlády ve veřejných zakázkách. V návrhu je to napsáno stručně: § 4b se zrušuje. Působí to nevinně a je to naprosto, naprosto zásadní. Dneska platí jasné: nesmí, ale pokud tohleto schválíte, bude nově otevřený prostor pro: může, posoudíme, vyložíme a pak to nějak zdůvodníme. To znamená, projde to, to znamená malá domů na dotacích pro Agrofert. ***"
  },
  "2025_22_00009": {
    "url": "https://www.psp.cz/eknih/2025ps/stenprot/022schuz/s022007.htm#r1",
    "cele_jmeno": "Tomio Okamura",
    "poradi": 9,
    "text": "Nyní vystoupí předseda Pirátů Zdeněk Hřib a připraví se předseda ODS Martin Kupka. Prosím, máte slovo."
  },
  "2025_22_00010": {
    "url": "https://www.psp.cz/eknih/2025ps/stenprot/022schuz/s022007.htm#r2",
    "cele_jmeno": "Zdeněk Hřib",
    "poradi": 10,
    "text": "Dobrý den, vážené kolegyně, vážení kolegové, vážený pane ministře zahraničí, když vás tady vidím, tak bychom mohli začít třeba nějakými titulkami ze zahraničního tisku, abychom se podívali tedy, jaký je obraz České republiky v zahraničí. Takže pro začátek tady mám (Ukazuje.): Financial Times, EU finds Czech Prime minister in breach of conflict-of-interest rules neboli Evropská unie shledala českého premiéra v porušení pravidel střetu zájmů. Potom tady mám Guardian: Czech Prime minister accused of conflict of interest over EU funds to businesses neboli Český premiér čelí obvinění ze střetu zájmů kvůli evropským penězům pro své firmy. Podívejte se, jakou nám děláte ostudu v Evropě. A nekončíme, máme tady další, Le Mond, Accusé de conflits d’Intérêts, le premier ministre tchèque favori des élections neboli Český premiér obviněný ze střetu zájmů favoritem voleb. Potom další Německo – Der Spiegel: Ermittlungen genen Tschechiens Premier Babis wieder aufgenommen neboli Vyšetřování českého premiéra Babiše bylo obnoveno. A potom El País, Španělsko: La justicia checa pide levantar la inmunidad del premier ministro Andrej Babis neboli Česká justice žádá o zbavení imunity premiéra Andreje Babiše. (Všechny materiály předává ministru Macinkovi.)\nTohle nejsou titulky z pirátského newsletteru ani výroky opozičních politiků, nejsou to ani komentáře na sociálních sítích od nějakých náhodných kolemjdoucích. Tohle jsou prostě titulky respektovaných zahraničních médií, která sledují, co se v České republice děje. A co nám říkají, co vidí? Vidí zemi, která se už roky, už roky točí kolem střetu zájmů jednoho člověka. Ano, ty titulky nejsou včerejší, je to průřez několika let, a vidí tady za ty roky premiéra spojeného s holdingem, který čerpá veřejné peníze, vidí stát, který místo ochrany svých občanů řeší to, jak ochránit penězovody do Agrofertu, a vidí Českou republiku, která to musí neustále dokola vysvětlovat v Evropě. A já se ptám: Opravdu tohle chceme? Opravdu chceme, aby Česká republika v evropských médiích byla symbolem střetu zájmů, dotačních kauz, ohýbání pravidel a rozkrádání veřejných prostředků?\nLidé v téhle zemi totiž řeší primárně to, kde budou bydlet, řeší drahé nájmy, řeší vysoké hypotéky, které jste mimochodem slibovali, že zlevníte, a lidé na ně teď nedosáhnou, a řeší, jestli jejich děti budou mít šanci zůstat, žít v tom městě, kde vyrostly, a řeší, jestli si mladá rodina třeba někdy vůbec bude moci pořídit byt a založit rodinu, a řeší, jestli obce budou mít peníze na výstavbu školy, školky, služby základní infrastruktury a tak dále. A co řeší vláda Andreje Babiše? Vláda Andreje Babiše řeší, jak ochránit penězovody pro Agrofert. A to je vlastně celé jádro problému neboli jádro pudla a každá další hodina, kterou tady ve Sněmovně trávíme řešením střetu zájmů Andreje Babiše, samozřejmě je další hodinou, kdy se nemůžeme věnovat řešení dalších problémů našich lidí, mladých rodin, seniorů, vlastně kohokoliv. Každá další debata o tom, jestli premiér může přes holding, svěřenské fondy nebo jakkoliv jinak s využitím libovolné právní kličky sahat na veřejné peníze, je čas, který potom chybí v řešení dostupného bydlení. Chybí rodinám, obcím, školám, regionům, ale my opravdu k tomu nemůžeme mlčet. My nemůžeme jenom přihlížet, jak si premiér tady hrabe erární peníze sobě do kapes, to bohužel opravdu možné není.\nAndrej Babiš a jeho dotační kauzy si nezaslouží, aby kvůli nim tahle země dalších deset let stála na místě, protože to nás nestojí jenom peníze, stojí nás to čas, stojí nás to energii, stojí nás to politickou pozornost, kterou bychom měli věnovat mladým lidem, rodinám, seniorům a hlavně tomu dostupnému bydlení. Přitom ta čísla mluví úplně jasně, 7 + 7 je 14, protože těch 14 miliard teď chybí pro to dostupné bydlení. Polovina z toho, 7 miliard, ty skončily podle dostupných informací v problémů neoprávněných dotací spojených s Andrejem Babišem a Agrofertem. Na to jsme dávali Andreji Babišovi ten QR kód, aby to mohl poslat zpátky, protože tam už soudy rozhodly, že to byly neoprávněně načerpané peníze, a dalších 7 miliard korun vláda teď přihodila ministru zemědělství v tomto roce do rozpočtu na dotace, které budou směřovat opět primárně velkým agrobaronům, tedy do prostředí, kde Agrofert hraje zásadní roli, takže to je dohromady 7 + 7, 14 miliard, a to je právě ta částka, co by nastartovala dostupné bydlení. 14 miliard – ty by mohly jít na výstavbu dostupných nájemních bytů, na podporu obcí, na pomoc mladým rodinám, na samoživitele, na seniory, prostě na lidi, kteří nechtějí luxus, nechtějí sosat zemědělské dotace jako pan Babiš, ale chtějí normální důstojný život. ***"
  },
  "2025_22_00011": {
    "url": "https://www.psp.cz/eknih/2025ps/stenprot/022schuz/s022010.htm#r1",
    "cele_jmeno": "Tomio Okamura",
    "poradi": 11,
    "text": "Nyní vystoupí předseda klubu KDU-ČSL Marian Jurečka, připraví se předseda ODS Martin Kupka a pak jako poslední přihlášku tady mám ministr zahraničí Petr Macinka. Tak prosím, máte slovo."
  },
  "2025_22_00012": {
    "url": "https://www.psp.cz/eknih/2025ps/stenprot/022schuz/s022010.htm#r2",
    "cele_jmeno": "Marian Jurečka",
    "poradi": 12,
    "text": "Dobrý den, vážené kolegyně, kolegové, pane předsedající, dobré odpoledne ještě jednou. Mě mrzí, že na této schůzi, která se týká našeho pana premiéra, tady pan premiér není ani tady nebyl v jejím úvodu, nehodlá vystoupit, protože určitě kdyby přišel s přednostním právem vystoupit, tak by tady mohl říci ten svůj pohled a vysvětlit některé věci.\nNa úvod chci tady ocenit vystoupení pana ministra zemědělství, který tady byl aspoň přítomen, alibisticky se neomluvil, ale byl tady.\nDrahá, nejdražší vládo, chci tady zarámovat tu situaci z pohledu běžného občana, kterému ta situace může přijít nepřehledná, protože téma evropských dotací je téma, kterému rozumí opravdu jenom velmi malá skupina lidí v této zemi, ale zkusím říct, o co tady jde opravdu velmi laickým pohledem. \nTy dopisy, kterými se tady argumentuje různě na různé strany, vlastně nám říkají jednu podstatnou věc. Dokud ta otázka právně nebude jednou provždy vyřešena, vyjasněna se zástupci Evropské komise, nemá Česká republika posílat v žádostech o platbu i finanční částky, které jdou do firem, které jsou spojeny s osobou Andreje Babiše. To znamená, v tento okamžik tady není verdikt, který by říkal: je to střet zájmů, není to střet zájmů, ale je tady jasné oznámení, povinně strohé, úřednické: neposílejte nám to, že chcete tyto peníze proplatit. Pokud jste je proplatili nebo je proplácet budete, je to čistě v ten okamžik zodpovědnost lidí, kteří sedí ve vládě a mají zodpovědnost za rozpočet této vlády. Jinými slovy, zase pro občana České republiky to znamená: státní rozpočet na rok 2026 nepočítal s tím, že by měl z národních zdrojů hradit zhruba až 2 miliardy korun v rámci dotací, které jdou do skupiny firem napojených na osobu Andreje Babiše. Pokud to teď stát bude vyplácet, tak to vyplácí z rozpočtových kapitol, ve kterých na to vůbec nebylo pamatováno. Normální rozumný hospodář by se v takové situaci zachoval způsobem, že by si řekl: Mám tady poměrně velké riziko, není rozhodnuto, já nemám jistotu větší než 50 procent, jestli ty dotace jsem vyplatil v souladu s pravidly a se zákony, tak by normální asi člen vlády řekl: Pojďme to pozastavit do doby, než se rozhodne.\nMusím říct, že pro mě, když jsem byl i čtyři roky ministrem zemědělství, je trošku s podivem, že se tady vláda k tomu tváří tak, že je tady jistota, že prostě jedeme dál, budeme vyplácet a za půl roku, za rok, možná za rok a půl přijde jednoznačně kladné rozhodnutí, že to všechno bylo v pořádku. Pokud to takhle nastane, tak dobře, vyšlo to, ale pokud toto nenastane, tak vám tady kladu konkrétní otázku a prosím, aby mě bylo zodpovězeno. Co bude dělat příslušný rezortní ministr nebo rezortní ministři – protože to se netýká jenom rezortu zemědělství – co bude dělat vláda s tím, jak ty peníze tedy bude zpátky vymáhat? Nebo je tam ponechá a byly zaplaceny čistě z peněz českého daňového poplatníka na konto toho, že se zvýší dluh České republiky, nebo tady zazní jasný závazek Andreje Babiše, že on ty peníze ze všech těch firem vrátí, protože to je věc, která v té veřejné debatě vůbec nezazněla. Já tady to chci postavit do role, ať si každý občan uvědomí, že pokud ty výplaty pojedou dál, mezitím nám Evropská komise to vyplácet nebude, tak to jde na vrub rozpočtových kapitol, především rezortu Ministerstva zemědělství, kde ty necelé 2 miliardy korun fakt letos nejsou a budou chybět. Doplní se tam? Doplní se z jakých zdrojů, nebo budou chybět na vrub toho, že v rámci rezortu zemědělství se budou škrtat peníze na pozemkové úpravy, vodovody, kanalizace, na jiné formy podpor pro zemědělství, rybářství, lesnictví, pro venkov? Zodpověděl to tady někdo z členů vlády? Ne, tomu se všichni vyhnuli. Nikdo neřekl, jakým způsobem se tyto peníze tedy případně doplní. Tak bych prosil, kdyby na tuto otázku případně členové vlády, kteří budou ještě dneska vystupovat s přednostním právem, odpověděli, jak vyřeší financování v letošním roce, pokud chtějí jako vláda vyplácet dál, z čeho ty peníze vezmou, z jaké konkrétní rozpočtové kapitoly kterého ministerstva, a na co tedy ty peníze budou chybět. To je moje vlastně první otázka a první velké upozornění. \nDruhá poznámka. Já bych měl velkou obavu, kdybych byl, ať už ministr rezortní, nebo ředitel Státního zemědělského intervenčního fondu, s ohledem na případnou zákonnou podmínku péče řádného hospodáře, protože pokud tyto věci nemám vyjasněné, dávám tomu zelenou nebo minimálně to nepozastavím do doby, kdy právně to nemám vyjasněno, tak si myslím, že to není postup v souladu s péčí řádného hospodáře, o které mluví zákon. \nAno, ministr zemědělství je zodpovědný více politicky, ale ředitel Státního zemědělského intervenčního fondu už zodpovědný opravdu naplno v pracovněprávním vztahu, v rovině zodpovědnosti za nakládání s veřejnými prostředky. To je další podle mě silný důvod, proč by se měli tito lidé chovat s nejenom péčí řádného hospodáře, ale s principem předběžné opatrnosti a říct: Do doby, než se to vyjasní, tak to pozastavujeme. \nPak chci jenom říct, ještě když jsem se podíval na ty dopisy a nedíval jsem se na to, co píšou média v České republice, ale podíval jsem se na to, co si mohu najít na webech a dostupných informacích jednotlivých orgánů Evropské komise, tak dopis DG AGRI nám neříká, je to všecko v pohodě. Dopis DG AGRI nám jenom říká: postupy a dohodnuté reporty bereme, že běží dál, ale neříká tam nějaká konkrétní formulace, to, že by řekl ten dopis: střet zájmů bereme za vyřešený, vyplácejte a všechny peníze budou dále propláceny z rozpočtu Evropské unie. To tam není. Jestli to tam někdo vidí, ať přijde, přečte tu formulaci a řekne: Jsme v pohodě, dopis DG Regia (je) vlastně taková věc, která se nás vůbec, ale vůbec netýká. Tak to bych byl rád, abychom si tady opravdu takto vyložili. ***"
  },
  "2025_22_00013": {
    "url": "https://www.psp.cz/eknih/2025ps/stenprot/022schuz/s022012.htm#r1",
    "cele_jmeno": "Patrik Nacher",
    "poradi": 13,
    "text": "Děkuji, pane předsedo. My jsme se vystřídali při řízení schůze, já vás tady také vítám.\nJenom připomínám, že jsme stále před bodem pořadu schůze, takže mohou vystupovat jenom poslanci s přednostním právem. V této chvíli bude na řadě pan ministr Petr Macinka, připraví se Martin Kupka.\nPane ministře, počkejte ještě chvilku, přečtu omluvy: Pavel Karpíšek celý jednací den – pracovní důvody, Jana Pastuchová od 17 hodin – osobní důvody, Lucie Sedmihradská celý jednací den – zahraniční cesta a Oto Klempíř do 16 hodin – pracovní důvody. V\n této chvíli máte slovo, pane ministře."
  },
  "2025_22_00014": {
    "url": "https://www.psp.cz/eknih/2025ps/stenprot/022schuz/s022012.htm#r2",
    "cele_jmeno": "Petr Macinka",
    "poradi": 14,
    "text": "Děkuji. Vážený pane předsedající, vážené kolegyně, vážení kolegové, když jsem si dnes ráno četl program této mimořádné schůze, a posléze tedy poslouchal několik trošku teatrálních vystoupení zástupců opozice, tak mě napadlo, že česká politika je vlastně v něčem nádherně konzervativní. Mění se vlády, mění se ministři, mění se politické strany, mění se ekonomická situace, ale některé věci zůstávají stále stejné, a jednou z nich je mimořádná schopnost části tady této Sněmovny svolat mimořádnou schůzi pokaždé, když jí dojdou skutečná témata. A tak jsme opět zde po letech, po desítkách podobných debat, po stovkách článků, po tisících televizních vystoupení, a opět posloucháme stejnou písničku: Andrej Babiš a jeho střet zájmů.\nKdybych nevěděl, že jsme v Poslanecké sněmovně roku 2026, tak bych si myslel, že někdo asi omylem pustil nějaký archivní záznam z roku 2018. A právě to je vlastně na té dnešní debatě celé nejzajímavější, protože ona vlastně ve skutečnosti vůbec není o střetu zájmů, ona je o něčem úplně jiném. Je to o tom, že část české politické scény se ani po letech nedokázala smířit s výsledkem demokratických voleb. Je to o tom, že část politické scény nedokázala přijmout skutečnost, že člověk, kterého upřímně nenávidí, opakovaně získává důvěru občanů, a je to taky o tom, že místo přemýšlení nad vlastními chybami se někteří stále snaží zoufale najít důvod, proč za jejich neúspěchy může někdo jiný.\nDámy a pánové, víte, že já nejsem členem hnutí ANO, nikdy jsem nebyl, a nejsem a nikdy jsem ani nebyl zaměstnancem Agrofertu. Nejsem ani právník premiéra Babiše, natož abych byl jeho mluvčím, ale jsem předsedou koaliční politické strany, která společně s hnutím ANO sedí v dnešní vládě, kterou samozřejmě pokládám za suverénně nejlepší vládu, jakou kdy naše země měla. A právě proto, že nejsem politik hnutí ANO, tak si mohu dovolit říct něco, co možná zaznívá méně častěji, než by mělo. Mě totiž na celé této debatě dnešní fascinuje především jedna věc, a to je, jak hluboce zakořeněná je v části české politiky nedůvěra vůči samotnému principu úspěchu. Jako člověk, který věří ve svobodný trh, v kapitalismus, v soukromé vlastnictví a v osobní odpovědnost považuji za absurdní, že se v této zemi už deset let vede téměř náboženská válka proti člověku především proto, že před vstupem do politiky vybudoval velkou a úspěšnou firmu. Děsí mě, kolik lidí uvažuje ve zvrácených schématech, jako by podnikatelský úspěch byl podezřelý, jako by vytváření pracovních míst bylo morální vadou, jako by bylo přijatelnější celý život žít z veřejných rozpočtů než nejprve něco vytvořit, vybudovat a nést za to zodpovědnost.\nJá si to samozřejmě nemyslím, nikdy si to myslet nebudu, protože vím na rozdíl od mnohých z vás, co tady sedíte, že kapitalismus není problém. Kapitalismus je naopak důvod, proč dnes žijeme mnohem lépe, než jak žily generace před námi. Soukromé podnikání určitě není hrozba, naopak soukromé podnikání je zdroj prosperity této země, a lidé, kteří budují firmy, investují vlastní kapitál, vytvářejí pracovní místa a nesou podnikatelské riziko, nejsou nepřáteli společnosti, ale naopak, jsou jedním z pilířů naší společnosti. ***"
  },
  "2025_22_00015": {
    "url": "https://www.psp.cz/eknih/2025ps/stenprot/022schuz/s022013.htm#r1",
    "cele_jmeno": "Patrik Nacher",
    "poradi": 15,
    "text": "Děkuji. Zatím poslední přihlášený s přednostním právem předseda ODS Martin Kupka. \nNež sem dorazí, přečtu jednu omluvu: Zdenka Crkvenjaš Němečková celý jednací den ze zdravotních důvodů. \n(K pultíku přichází s úsměvem poslanec Kupka, s taktéž usmívajícím se ministrem Macinkou se vzájemně zdraví.) \nVidím, že je tady dobrá nálada. Takže, pane předsedo, máte slovo."
  },
  "2025_22_00016": {
    "url": "https://www.psp.cz/eknih/2025ps/stenprot/022schuz/s022013.htm#r2",
    "cele_jmeno": "Martin Kupka",
    "poradi": 16,
    "text": "Vážený pane předsedající, dámy a pánové, to bylo pozoruhodné poslouchat ten více cenný projev (Poslanec Kupka se pootáčí do ministerských lavic.) pana ministra zahraničí, který kritizoval nálepkování, aby pak nálepkoval od začátku do konce. A kromě toho nálepkování říká, že jsme posedlí Andrejem Babišem. Já si matně uvědomuju, co bylo na billboardech Motoristů: „Pohlídáme Andreje Babiše“ tam bylo (Gestilujuje a otáčí se k ministrovi Macinkovi.), pamatujete? (Ministr Macinka s úsměvem přikyvuje.) Výborné. A když tohle heslo dáte dohromady s tím, co provádíte, a s tím, co říkáte teď, tak to přece nedává vůbec žádný smysl. \nPak jste mluvil o milionech voličů, kteří vám umožnili sedět ve vládě Andreje Babiše: 380 000 to bylo – to nejsou miliony, to je 380 000. Koalice SPOLU měla 1 313 000 hlasů, abychom si to jenom vyjasnili. Chápu, že ve vašich projevech to k realitě může být hodně daleko, ale hodně se zrazujete a ukazujete na svoji vlastní tupost (Ministr Macinka gestikuluje.) a to by vlastně jako pro ministra zahraničí nebyla ta pravá vizitka. \nPojďme ale opravdu k tomu, co tuhle schůzi vyvolalo. (Gestikuluje.) Ještě jedna věc, které jsem si všiml (Otáčí se k ministrovi Macinkovi.): oslava kapitalismu a tržního hospodářství. To je (Přikyvuje.), to je naše písnička (Pootáčí se opět k ministrovi Macinkovi.), akorát jste zapomněl, že ten pán, co vám dělá šéfa ve vládě, při každé příležitosti hovoří o tom, jak těch předchozích třicet nebo třicet pět let, jak to bylo špatné, jak to byl projev mafiánství, jak to tady nefungovalo, jak to tady i lidé, se kterými jste spolupracoval, divně vedli. To je taky tentýž Andrej Babiš. To jste si – jak se to říká? – trochu nadělal do vlastního hnízda. (Ministr Macinka z lavice: Si to vysvětlíme.) Tak jenom, aby – že si to vysvětlíte, to bude možná zajímavé vysvětlovat, jak to s tím kartelem myslel, když se sám na něm podílel. Drze to může sice vyslovovat, ale ve výsledku tím fackuje vás. Jenom si to musíte dát nějak dohromady, aby to dávalo smysl. \nŘíkáte, že se bráníme úspěchu – vůbec ne, naopak. ODS od samého začátku dává a vytváří příležitost pro ty, kteří to se soutěží a férovou soutěží myslí vážně, aby byli úspěšní, aby šli nahoru. Akorát si víc ceníme těch, kteří úspěch staví opravdu na výsledcích své práce, na podnikatelském riziku, a ne na dotační politice. Mimochodem (Pootáčí se k ministrovi Macinkovi.), s dotacemi (Gestikuluje.) – jsem zaslechl, ale bylo to, já vím, jenom v programu, jinak v realitě to už nefunguje – prý také máte problém. ***"
  },
  "2025_22_00017": {
    "url": "https://www.psp.cz/eknih/2025ps/stenprot/022schuz/s022015.htm#r1",
    "cele_jmeno": "Patrik Nacher",
    "poradi": 17,
    "text": "Počkejte, pane předsedo, tady už teďka ten hluk je asi příliš velký. Poprosím kolegy vlevo, jestli by mohli ty diskuse ztišit.\nTak děkuji, můžete."
  },
  "2025_22_00018": {
    "url": "https://www.psp.cz/eknih/2025ps/stenprot/022schuz/s022015.htm#r2",
    "cele_jmeno": "Martin Kupka",
    "poradi": 18,
    "text": "A za těchto podmínek nastává to, že stát přestává reálně fungovat pro lidi a mění se na stroj na peníze pro toho, kdo je u moci. To je definice babišismu a říkám zcela otevřeně, že tomu budeme bránit, a budeme tomu bránit s konkrétními argumenty a právními stanovisky, seč budeme moct, a proto také jsem osobně oslovil Zuzanu Brücknerovou, která v tuto chvíli zastává roli nejvyššího státního tajemníka, aby na jednotlivých ministerstvech prověřila, jestli v České republice nedochází k porušování služebního zákona a základního pravidla nezávislosti státních úředníků. Za jakých okolností rozhodli o tom, že nebudou vymáhat povinnosti? Za jakých okolností například vyplácejí dotace, přestože existuje reálné riziko, že je stát nikdy neproplatí a že budeme absolvovat další soudní spory o vratku těch dotací, protože tohle přece lidé platit nemají, pokud někdo porušuje zákon?\nA jestli se někdo nad tím pozastavujete, tak se fakt podívejte na návrh zákona, který předložila skupina vládních poslanců. Podívejte se na to, co tam říkáte, že vlastně střet zájmů nebude existovat jenom v případě, že by se týkal přímo firem příslušného ministra, ale o premiérovi se tam nemluví a nemluví se ani o tom, že kdyby se jednalo o firmu vládního kolegy, tak taky střet zájmů neexistuje. Tohle je fakt nepředstavitelné. A když jsem mluvil o tom vymáhání peněz, proč zkracujete tu lhůtu pro vymahatelnost na 4 roky? Proto, aby to definitivně bylo zapomenuto? Proto, aby bylo jasné, že svému šéfovi budete prostě měřit jiným metrem a že takzvaně za něj zakryjete střet zájmů? Tohle ale fakt není normální a to rozhodně není projev naší nenávisti vůči Andreji Babišovi. To je jenom konkrétní úkol opozice bránit peníze daňových poplatníků a bránit pravidla, která v České republice mají existovat, a naopak to, co ukazujete vy, že vůbec přijdete s takovým návrhem zákona, je učebnicový příklad snahy o ovládnutí státu, o mašinerii, která se rozeběhla kolem premiérových dotací, a najednou to vidíme, jak se mění postoj i jednotlivých úřadů, a mě zajímá, jakým způsobem odpoví nejvyšší státní tajemník, respektive Zuzana Brücknerová, která v té roli vystupuje, na to, jestli nepůsobili politickým vlivem ministři vlády Andreje Babiše na úředníky, kteří rozhodovali o vyplacení dotací. Kdo dával ty pokyny? Jakým způsobem je zdokladováno, že ty dotace možné vyplatit bylo? A zároveň se samozřejmě budeme ptát i na to, jak jsem zmiňoval, kdo rozhodl o tom, že stát nebude vymáhat něco, k čemu existují pravomocné rozsudky soudů, dokonce soudů vyšší instance? Není vůbec sporu o tom, že způsob vládnutí Andreje Babiše má dosah do jednotlivých ministerstev. Možná nemá tolik dosah na Úřad vlády, protože tam rozhoduje Tünde Bartha, a Andrej Babiš v tom potom tak zvláštně bruslí a zapomíná, co dělal a říkal před dvěma měsíci, ale na jednotlivá ministerstva se tedy rozhodně působit snaží.\nA jestli někdo tímhle způsobem vysává stát, jestli tímhle způsobem nakládá s veřejnými prostředky na úkor jasných a jednotných pravidel pro všechny, tak to prostě je chování ekonomického parazita. V okamžiku, kdyby Brusel sáhl k plošnému pozastavení dotací, přijdou o důležité finanční prostředky všechny firmy. Přijdou o ně všichni, kteří v oblasti zemědělství samozřejmě na ně mají nárok anebo o ně usilují za férových pravidel, a férovost tržního prostředí je jeden ze základních předpokladů, aby Česká republika normálně fungovala, a ano, na férových podmínkách tržního hospodářství budeme fungovat, i když se to třeba Motoristům nelíbí – teď, jak hlídají Andreje Babiše, tak už asi nemůže, protože by tím odhalovali sami sebe a svoje pokrytectví – tak ale my na tom rozhodně trvat budeme. A znovu říkáme, přece není náhoda, není smyšlenka, když říká Evropská komise, že chce vědět nejenom, jak se vypořádal Andrej Babiš s Agrofertem, když ho převedl do svěřenského fondu, ale jak je to se SynBiolem a jak je to s holdingem Hartenberg. To jsou další firmy Andreje Babiše a Andrej Babiš tady jasně ukazuje, že střet zájmů nevyřešil, protože do toho svěřenského fondu vložil, a to je i jeho vlastní prohlášení, jenom společnost Agrofert, takže je tu obrovská otázka, jak to vlastně je v České republice teď s plněním základních pravidel.\nKdyž jsme se obrátili na nejvyššího státního tajemníka, očekáváme odpověď a máme ji dokonce slíbenou, že bude prověřeno, na základě jakých dokumentů jednala jednotlivá ministerstva a úředníci, protože tady platí totéž, co vlastně v Maďarsku. Tam se taky děly na některých ministerstvech pozoruhodné věci a dneska ti úředníci, když příběh Orbán skončil, jsou vyděšení k smrti, protože se najednou začíná někdo ptát: Respektovali jste pravidla? Respektovali jste platné zákony? Na základě čeho jste rozhodovali na jednotlivých ministerstvech? Já bych byl nerad, aby v České republice se zopakoval příklad Viktora Orbána a orbánismu.\nAle to, co se ukazuje, nás nutně vede k závažným otázkám, jakým způsobem se teď uvolňování prostředků pro Agrofert odehrálo a na základě jakých konkrétních podnětů, jakých případných příkazů, kdo o tom rozhodoval a zda na něho ministři vlády Andreje Babiše nevyvíjeli politický tlak. A znovu zdůrazňuju, jde nám o základní fungování státu, kde pravidla mají platit pro všechny, kdy Andrej Babiš měl zákonnou lhůtu k vyřešení střetu zájmů 30 dnů od jmenování. Už je to půlrok a stále není jasné, jak to vlastně je a jak vypadá ten status svěřenského fondu. Je přece přirozené, že se na to ptáme, a je úplně normální, že se na to po zkušenostech deset let zpět ptá i Evropská komise, a znovu zdůrazňuju precedent tehdy svěřenských fondů, kam Andrej Babiš vkládal svůj majetek, a nezávislý audit určil, že to neodpovídalo evropské legislativě a že se mu tím nepodařilo zabránit střetu zájmů.\nZnovu nedávno Petr Bendl položil otázku na základě veřejných dat, kdo dluží Andreji Babišovi víc než 1,5 miliardy korun. Pokud je to Agrofert – nevíme – pokud to je on, tak je ale přirozené, že bez jakéhokoliv svěřenského fondu a dalších náležitostí pak musí mít zájem na tom, aby ty prostředky byly splaceny, je to přece zájem každého věřitele, a v ten okamžik bude mít dál Andrej Babiš zájem na tom, aby Agrofert prosperoval. Ale my se v tomto směru jenom ptáme, jenom se nedočkáváme odpovědí, a bohužel asi kvůli zbabělosti tady Andrej Babiš není, aby tady jasně pověděl, jak to je. Ale bude se ptát nejenom současná opozice, ale budou se ptát logicky i nezávislé instituce, protože i veřejnost, ale i ty instituce prostě mají právo vědět, jak je to s konkrétními podmínkami toho svěřenského fondu. Ve veřejných zdrojích se totiž objevilo, že to navždy, o kterém mluvil Andrej Babiš, je tedy fakt obrovský eufemismus, že v okamžiku, kdy se Andrej Babiš vrátí z vlády, rezignuje nebo bude odvolán nebo ta vláda skončí, tak se veškerý majetek vrací zpět jeho rodině. Kdy je řečeno, že pak dál nebude v nějaké roli o tom majetku rozhodovat, a už budou zaplacené ty peníze, o kterých tu byla řeč nebo nebudou – jak to přesně stojí? ***"
  },
  "2025_22_00019": {
    "url": "https://www.psp.cz/eknih/2025ps/stenprot/022schuz/s022016.htm#r1",
    "cele_jmeno": "Patrik Nacher",
    "poradi": 19,
    "text": "Pardon. Pardon, pane předsedo. Poprosím o klid. Já vím, že se postupně vracíte do sálu, já jsem vás k tomu vyzval, gongoval jsem, ale poprosím o klid. Kolegyně, kolegové vlevo, vpravo je klid. \nTak zkuste, pane předsedo. Můžete, můžete."
  },
  "2025_22_00020": {
    "url": "https://www.psp.cz/eknih/2025ps/stenprot/022schuz/s022016.htm#r2",
    "cele_jmeno": "Martin Kupka",
    "poradi": 20,
    "text": "Oč tu jde? Jde tu přece o to, aby Andrej Babiš dal na stůl fakta, aby řekl, jak se se střetem zájmů vypořádal. Na to mají právo občané, těm to sliboval, má na to právo prezident a my samozřejmě na těch odpovědích budeme trvat. Trváme na nich od první chvíle a upozorňujeme na jasné nedostatky v té odpovědi. Proč nebyl vložen SynBiol a Hartenberg do nějakého svěřenského fondu? Jak vypadá ten status? Jak se skutečně vypořádává se střetem zájmů? Myslíte to vážně, anebo je to jenom hra s občany České republiky? Mají tady platit pravidla pro všechny stejně, nebo jste opravdu zvolili cestu nového státního uspořádání babišistánu, kde se prostě Andreji Babišovi měří jiným metrem?\nJá vím, že to neradi posloucháte, ale tohle jsou reálné otázky, na které se bráníte odpovědět, protože je to nepříjemné, anebo na to nemáte odpověď. Ve výsledku ale, pokud na to neodpovíte, tak lidé v České republice, a teď musím říct ještě důležitou zprávu i pro předsedkyni vašeho poslaneckého klubu, i vaši voliči, i když nechtějí, tak zaplatí dotace Andreje Babiše. Anebo jste jim řekli, že budou platit byznys Agrofertu? Myslím, že ne, že tohle jste jim neřekli, a neřekli to ani Motoristé. A dokonce si myslím, že to neřekli ani představitelé SPD, že by tímhle způsobem Andreji Babišovi, který s nimi hraje nefér hru, takhle chtěli umetat chodníček. \nPojďme opravdu do finále, protože je teď na vás, je na vládní koalici, jestli otevře program téhle schůze a dá příležitost Andreji Babišovi, aby na tohle odpověděl. Někteří se tváříte, že už na to máte dávno odpověď, ale to jenom ukáže bohužel zbabělost v tom přístupu a neférovost, protože tyhle otázky nejsou jenom otázkou opozice, jsou otázkou lidí, kteří v České republice platí daně a mají právo na to, aby je český stát chránil, aby chránil férové podmínky – férové podmínky podnikání a férové podmínky dotací, které se v České republice podnikatelům v různých oblastech prostě rozdávají. Občané na tohle mají právo. \nA já říkám zcela jasně, že my jako demokratická opozice nepřestaneme bojovat za to, aby se v České republice naplňovala vláda práva, a nepřestaneme bojovat za to, abyste těmihle kroky nenormalizovali podmínky v České republice, aby tady nevítězil babišismus, aby tady nevítězily snahy legalizovat zlodějinu, ale aby Česká republika dál fungovala jako férová země, která pro všechny občany je připravena zajistit a garantovat spravedlivé podmínky. Děkuji za pozornost. (Potlesk z lavic ODS.) ***"
  },
  "2025_22_00021": {
    "url": "https://www.psp.cz/eknih/2025ps/stenprot/022schuz/s022017.htm#r1",
    "cele_jmeno": "Patrik Nacher",
    "poradi": 21,
    "text": "Děkuji, pane předsedo. V této chvíli zde nemám žádného poslance s přednostním právem, takže jsem přizval poslance z kuloárů. \nMezitím ještě přečtu omluvy: David Pražák od 17 do 19 hodin z pracovních důvodů, Michaela Šebelová od 15 hodin – pracovní důvody, Renáta Zajíčková celý jednací den – pracovní důvody. \nJá už jsem gongoval několikrát při závěru vystoupení předsedy Martina Kupky, takže si myslím, že už to asi nemusíme natahovat.\nNejprve vás všechny odhlásím. Kolegyně, kolegové, přihlaste se svými identifikačními kartami. Ano, kolegové, když jsem vás odhlásil, tak už nemusíte ťukat. S náhradní kartou číslo 1 bude hlasovat místopředseda Jan Skopeček. \n \nV této chvíli tedy budeme hlasovat o celém návrhu pořadu 22. schůze Poslanecké sněmovny, jak byl písemně předložen. \nZahajuji hlasování. Kdo je pro? Ať zvedne ruku a stiskne tlačítko. Kdo je proti?\nHlasování číslo 2, přihlášeno 151 poslanců, pro 66, proti 85. Návrh nebyl přijat.\n \nPořad schůze nebyl schválen, tímto končím 22. schůzi Poslanecké sněmovny.\nPřipomínám, kolegyně, kolegové, že my se zde sejdeme na 23. schůzi v 15.00. \nNicméně mám tady mimořádnou žádost našeho kolegy v této pauze, kolegy Kotta, který se chce zřejmě rozloučit, tak jsem i místopředsedy klubu o tom informoval.\nTak, pane poslanče."
  },
  "2025_22_00022": {
    "url": "https://www.psp.cz/eknih/2025ps/stenprot/022schuz/s022017.htm#r2",
    "cele_jmeno": "Josef Kott",
    "poradi": 22,
    "text": "Děkuji pěkně za slovo, pane místopředsedo. Milé kolegyně, vážení kolegové, protože mám před sebou poslední schůzi v této ctěné Sněmovně, tak bych vám chtěl všem poděkovat za spolupráci, popřát vám vše dobré do vaší práce a hlavně hodně zdraví vám i vašim blízkým do dalších let. Ještě jednou děkuji. (Potlesk v celém sále.)"
  },
  "2025_22_00023": {
    "url": "https://www.psp.cz/eknih/2025ps/stenprot/022schuz/s022017.htm#r3",
    "cele_jmeno": "Patrik Nacher",
    "poradi": 23,
    "text": "Já vám všem děkuju za velkorysost a znovu připomínám: v 15 hodin zahájíme 23. schůzi. Zatím přeji pěkné odpoledne.\nJeště přečtu jednu omluvu: Jan Richter celý jednací den z rodinných důvodů.\n \n(Schůze skončila v 14.41 hodin.) ***"
  }
}
