{
  "slug": "navrh-na-zmeny-ve-slozeni-organu-poslanecke-snem",
  "nazev": "Návrh na změny ve složení orgánů Poslanecké sněmovny",
  "datum": "06.03.2026",
  "verdikt": "schvaleno",
  "predmet_lidsky": "změnách ve složení orgánů sněmovny a souvisejících volbách",
  "koho": [
    "Koho se to týká? Politické strany a orgány sněmovny. Občana na ulici to netrefí."
  ],
  "fakty": [
    {
      "text": "Hlasování číslo 70, pro 168, proti nikdo. Návrh byl přijat.",
      "source": "steno",
      "steno_id": "2025_10_00713",
      "citace": "Hlasování číslo 70, pro 168, proti nikdo. Návrh byl přijat."
    },
    {
      "text": "Hlasování číslo 72, pro 117, proti 33. Návrh byl přijat.",
      "source": "steno",
      "steno_id": "2025_10_00713",
      "citace": "Hlasování číslo 72, pro 117, proti 33. Návrh byl přijat."
    },
    {
      "text": "Hlasování číslo 75, pro 120, proti 11. Návrh byl přijat.",
      "source": "steno",
      "steno_id": "2025_10_00713",
      "citace": "Hlasování číslo 75, pro 120, proti 11. Návrh byl přijat."
    }
  ],
  "publikovat": true,
  "priorita": 2,
  "nadpis": "Obsazování postů ve sněmovně",
  "lead": "Páteční dopoledne patřilo volbám do orgánů: VZP, Český rozhlas, Česká televize i ochránce práv dětí. Všechno prošlo.",
  "pointa": "U správy VZP bylo 33 hlasů proti, u ochránce dětí 11. Jinak klidná obsazování postů bez velkého příběhu.",
  "mean": "Sněmovna si obsadila výbory a rady, které dohlížejí na instituce od pojišťovny po média. Jde o moc uvnitř parlamentu, ne o zákon pro lidi.",
  "pocet_hlasovani": 1,
  "proslo": true,
  "steno_slov": 14735
}
