{
  "slug": "rozpocet-sfdi-na-rok-2026",
  "nazev": "Rozpočet SFDI na rok 2026",
  "datum": "11.03.2026",
  "verdikt": "schvaleno",
  "predmet_lidsky": "rozpočet SFDI na rok 2026",
  "koho": [
    "Dotkne se vás, když jedete po silnici, stavíte nebo farmáříte; jinak spíš suché číslo v tabulce."
  ],
  "fakty": [
    {
      "text": "A jdeme k bodu číslo 58.Rozpočet Státního fondu dopravní infrastruktury na rok 2026 a střednědobý výhled na roky 2027 a 2028/sněmovní tisk 91/ Tento materiál uvede ministr dopravy Ivan Bednárik.",
      "source": "steno",
      "steno_id": "2025_10_01378",
      "citace": "A jdeme k bodu číslo 58.Rozpočet Státního fondu dopravní infrastruktury na rok 2026 a střednědobý výhled na roky 2027 a 2028/sněmovní tisk 91/ Tento materiál uvede ministr dopravy Ivan Bednárik."
    },
    {
      "text": "Od 20.00 z osobních důvodů se omlouvá pan poslanec Patrik Nacher.",
      "source": "steno",
      "steno_id": "2025_10_01378",
      "citace": "Od 20.00 z osobních důvodů se omlouvá pan poslanec Patrik Nacher."
    },
    {
      "text": "A prosím, aby se i tady ke stolku zpravodajů přesunul zpravodaj hospodářského výboru, pan poslanec Martin Kolovratník.",
      "source": "steno",
      "steno_id": "2025_10_01378",
      "citace": "A prosím, aby se i tady ke stolku zpravodajů přesunul zpravodaj hospodářského výboru, pan poslanec Martin Kolovratník."
    },
    {
      "text": "V sále je velký hluk.",
      "source": "steno",
      "kind": "scene",
      "steno_id": "2025_10_01379",
      "citace": "(V sále je velký hluk.)"
    }
  ],
  "publikovat": true,
  "priorita": 3,
  "nadpis": "Prošlo to",
  "pocet_hlasovani": 1,
  "proslo": true,
  "signaly": {
    "proti_max": 13,
    "pritomno_min": 177,
    "jednomyslne": false,
    "spor": true,
    "prazdny_sal": false
  },
  "steno_slov": 5004,
  "mean": "Sněmovna schvalovala rozpočet Státního fondu dopravní infrastruktury na rok 2026. Peníze jdou na silnice, mosty a další dopravní stavby."
}
