{
  "slug": "vl-n-z-o-ucetnictvi-souvisejici-eu",
  "nazev": "Vl. n. z. o účetnictví - související - EU",
  "datum": "12.03.2026",
  "verdikt": "schvaleno",
  "predmet_lidsky": "o účetnictví - související",
  "koho": [],
  "fakty": [
    {
      "text": "Peštová Berenika od 10 hodin do 13 hodin zdravotní důvody, Tureček Karel celý jednací den zdravotní důvody a Metnar Lubomír od 13 hodin pracovní důvody.",
      "source": "steno",
      "steno_id": "2025_10_01499",
      "citace": "Peštová Berenika od 10 hodin do 13 hodin zdravotní důvody, Tureček Karel celý jednací den zdravotní důvody a Metnar Lubomír od 13 hodin pracovní důvody."
    },
    {
      "text": "Hlasování číslo 252, přihlášeno 136 poslanců, pro 130, proti nikdo.",
      "source": "steno",
      "steno_id": "2025_10_01499",
      "citace": "Hlasování číslo 252, přihlášeno 136 poslanců, pro 130, proti nikdo."
    },
    {
      "text": "Návrh zákona o účetnictví vychází z věcného záměru, který byl vládou schválen již v říjnu 2020.",
      "source": "steno",
      "steno_id": "2025_10_01500",
      "citace": "Návrh zákona o účetnictví vychází z věcného záměru, který byl vládou schválen již v říjnu 2020."
    }
  ],
  "publikovat": false,
  "priorita": 0,
  "nadpis": "Prošlo to",
  "pocet_hlasovani": 2,
  "proslo": true
}
